mcp_notion/__init__.py
mcp_notion/server.py
mcp_notion-0.0.2.dist-info/METADATA
mcp_notion-0.0.2.dist-info/WHEEL
mcp_notion-0.0.2.dist-info/entry_points.txt
mcp_notion-0.0.2.dist-info/top_level.txt
mcp_notion-0.0.2.dist-info/RECORD
